honeybee/__init__.py
honeybee/_version.py
honeybee/honeybee.py
honeybee-0.1.0a3.dist-info/METADATA
honeybee-0.1.0a3.dist-info/RECORD
honeybee-0.1.0a3.dist-info/WHEEL
honeybee-0.1.0a3.dist-info/top_level.txt
