Metadata-Version: 2.1
Name: honeybee
Version: 0.1.0a3
Summary: An artificial bee colony implementation in Python
Home-page: https://github.com/Engineero/honeybee
Author: Engineero
Author-email: engineerolabs@gmail.com
License: UNKNOWN
Project-URL: Documentation, https://engineero.github.io/honeybee
Project-URL: Source, https://github.com/Engineero/honeybee
Project-URL: Tracker, https://github.com/Engineero/honeybee/issues
Keywords: abc artificial bee colony optimization
Platform: UNKNOWN
Classifier: Development Status :: 2 - Pre-Alpha
Classifier: Environment :: Console
Classifier: Intended Audience :: Developers
Classifier: Intended Audience :: Science/Research
Classifier: License :: OSI Approved :: MIT License
Classifier: Natural Language :: English
Classifier: Operating System :: OS Independent
Classifier: Programming Language :: Python
Classifier: Programming Language :: Python :: 3
Classifier: Programming Language :: Python :: 3.3
Classifier: Programming Language :: Python :: 3.4
Classifier: Programming Language :: Python :: 3.5
Classifier: Programming Language :: Python :: 3.6
Classifier: Topic :: Scientific/Engineering
Classifier: Topic :: Scientific/Engineering :: Artificial Intelligence
Classifier: Topic :: Scientific/Engineering :: Artificial Life
Classifier: Topic :: Utilities
